{
 "category_id": 4286,
 "name": "Case 580N & 580 Super N Pin Kits",
 "url": "/c/case-580n-580-super-n-backhoe-pin-kits/",
 "image": "https://cdn11.bigcommerce.com/s-knh0cnq2u8/images/stencil/original/image-manager/case-580n-pin-bushing-kit.jpg?t=1748533710",
 "img_w": 3755,
 "img_h": 1701,
 "style": "black-callout",
 "circles": [
  {
   "i": 0,
   "x_px": 527.4,
   "y_px": 172.2,
   "r_px": 39.4,
   "x": 14.05,
   "y": 10.12,
   "r": 1.05
  },
  {
   "i": 1,
   "x_px": 803.4,
   "y_px": 307.8,
   "r_px": 101.3,
   "x": 21.4,
   "y": 18.1,
   "r": 2.7
  },
  {
   "i": 2,
   "x_px": 913.8,
   "y_px": 328.2,
   "r_px": 10.2,
   "x": 24.34,
   "y": 19.29,
   "r": 0.27
  },
  {
   "i": 3,
   "x_px": 1811.4,
   "y_px": 407.4,
   "r_px": 69.6,
   "x": 48.24,
   "y": 23.95,
   "r": 1.85
  },
  {
   "i": 4,
   "x_px": 1921.8,
   "y_px": 403.8,
   "r_px": 29.7,
   "x": 51.18,
   "y": 23.74,
   "r": 0.79
  },
  {
   "i": 5,
   "x_px": 1678.2,
   "y_px": 450.6,
   "r_px": 78.9,
   "x": 44.69,
   "y": 26.49,
   "r": 2.1
  },
  {
   "i": 6,
   "x_px": 780.6,
   "y_px": 496.2,
   "r_px": 63.0,
   "x": 20.79,
   "y": 29.17,
   "r": 1.68
  },
  {
   "i": 7,
   "x_px": 1597.8,
   "y_px": 462.6,
   "r_px": 18.2,
   "x": 42.55,
   "y": 27.2,
   "r": 0.48
  },
  {
   "i": 8,
   "x_px": 2197.8,
   "y_px": 528.6,
   "r_px": 39.3,
   "x": 58.53,
   "y": 31.08,
   "r": 1.05
  },
  {
   "i": 9,
   "x_px": 2796.6,
   "y_px": 558.6,
   "r_px": 37.7,
   "x": 74.48,
   "y": 32.84,
   "r": 1.0
  },
  {
   "i": 10,
   "x_px": 727.8,
   "y_px": 636.6,
   "r_px": 41.7,
   "x": 19.38,
   "y": 37.43,
   "r": 1.11
  },
  {
   "i": 11,
   "x_px": 2515.8,
   "y_px": 627.0,
   "r_px": 12.9,
   "x": 67.0,
   "y": 36.86,
   "r": 0.34
  },
  {
   "i": 12,
   "x_px": 1944.6,
   "y_px": 749.4,
   "r_px": 51.2,
   "x": 51.79,
   "y": 44.06,
   "r": 1.36
  },
  {
   "i": 13,
   "x_px": 2957.4,
   "y_px": 741.0,
   "r_px": 39.3,
   "x": 78.76,
   "y": 43.56,
   "r": 1.05
  },
  {
   "i": 14,
   "x_px": 1289.4,
   "y_px": 780.6,
   "r_px": 39.4,
   "x": 34.34,
   "y": 45.89,
   "r": 1.05
  },
  {
   "i": 15,
   "x_px": 1782.6,
   "y_px": 793.8,
   "r_px": 71.0,
   "x": 47.47,
   "y": 46.67,
   "r": 1.89
  },
  {
   "i": 16,
   "x_px": 2220.6,
   "y_px": 787.8,
   "r_px": 35.3,
   "x": 59.14,
   "y": 46.31,
   "r": 0.94
  },
  {
   "i": 17,
   "x_px": 665.4,
   "y_px": 899.4,
   "r_px": 67.0,
   "x": 17.72,
   "y": 52.87,
   "r": 1.78
  },
  {
   "i": 18,
   "x_px": 1679.4,
   "y_px": 861.0,
   "r_px": 36.5,
   "x": 44.72,
   "y": 50.62,
   "r": 0.97
  },
  {
   "i": 19,
   "x_px": 2173.8,
   "y_px": 952.2,
   "r_px": 16.7,
   "x": 57.89,
   "y": 55.98,
   "r": 0.45
  },
  {
   "i": 20,
   "x_px": 2268.6,
   "y_px": 976.2,
   "r_px": 43.1,
   "x": 60.42,
   "y": 57.39,
   "r": 1.15
  },
  {
   "i": 21,
   "x_px": 2645.4,
   "y_px": 942.6,
   "r_px": 35.0,
   "x": 70.45,
   "y": 55.41,
   "r": 0.93
  },
  {
   "i": 22,
   "x_px": 2899.8,
   "y_px": 1014.6,
   "r_px": 26.0,
   "x": 77.23,
   "y": 59.65,
   "r": 0.69
  },
  {
   "i": 23,
   "x_px": 833.4,
   "y_px": 1032.6,
   "r_px": 39.4,
   "x": 22.19,
   "y": 60.71,
   "r": 1.05
  },
  {
   "i": 24,
   "x_px": 1389.0,
   "y_px": 1037.4,
   "r_px": 13.6,
   "x": 36.99,
   "y": 60.99,
   "r": 0.36
  },
  {
   "i": 25,
   "x_px": 2315.4,
   "y_px": 1097.4,
   "r_px": 81.5,
   "x": 61.66,
   "y": 64.51,
   "r": 2.17
  },
  {
   "i": 26,
   "x_px": 2790.6,
   "y_px": 1086.6,
   "r_px": 41.8,
   "x": 74.32,
   "y": 63.88,
   "r": 1.11
  },
  {
   "i": 27,
   "x_px": 1479.0,
   "y_px": 1164.6,
   "r_px": 101.3,
   "x": 39.39,
   "y": 68.47,
   "r": 2.7
  },
  {
   "i": 28,
   "x_px": 2681.4,
   "y_px": 1147.8,
   "r_px": 15.9,
   "x": 71.41,
   "y": 67.48,
   "r": 0.42
  },
  {
   "i": 29,
   "x_px": 1320.6,
   "y_px": 1325.4,
   "r_px": 15.2,
   "x": 35.17,
   "y": 77.92,
   "r": 0.4
  },
  {
   "i": 30,
   "x_px": 1182.6,
   "y_px": 1419.0,
   "r_px": 37.5,
   "x": 31.49,
   "y": 83.42,
   "r": 1.0
  },
  {
   "i": 31,
   "x_px": 1458.6,
   "y_px": 1409.4,
   "r_px": 36.5,
   "x": 38.84,
   "y": 82.86,
   "r": 0.97
  },
  {
   "i": 32,
   "x_px": 1338.6,
   "y_px": 1483.8,
   "r_px": 29.8,
   "x": 35.65,
   "y": 87.23,
   "r": 0.79
  }
 ]
}